{
  "name": "NormalMapBake",
  "input": {
    "options" : {},
    "inputs": [
      {
        "inputName": "lowpoly",
        "type": "mesh",
        "average_normals": "UseExportedNormals"
      },
      {
        "inputName": "highpoly",
        "type": "mesh",
        "average_normals": "UseExportedNormals"
      }
    ]
  },
  "output": {
    "options": {},
    "outputs": [
      {
        "outputName": "normal",
        "type": "texture",
        "genName": "gen_normals"
      }
    ]
  }
}